MANIFEST.in
README.md
setup.cfg
setup.py
dcos_shakedown.egg-info/PKG-INFO
dcos_shakedown.egg-info/SOURCES.txt
dcos_shakedown.egg-info/dependency_links.txt
dcos_shakedown.egg-info/entry_points.txt
dcos_shakedown.egg-info/not-zip-safe
dcos_shakedown.egg-info/requires.txt
dcos_shakedown.egg-info/top_level.txt
shakedown/__init__.py
shakedown/cli/__init__.py
shakedown/cli/helpers.py
shakedown/cli/main.py
shakedown/dcos/__init__.py
shakedown/dcos/agent.py
shakedown/dcos/cluster.py
shakedown/dcos/command.py
shakedown/dcos/config.py
shakedown/dcos/docker.py
shakedown/dcos/file.py
shakedown/dcos/helpers.py
shakedown/dcos/marathon.py
shakedown/dcos/master.py
shakedown/dcos/network.py
shakedown/dcos/package.py
shakedown/dcos/security.py
shakedown/dcos/service.py
shakedown/dcos/spinner.py
shakedown/dcos/task.py
shakedown/dcos/zookeeper.py