Metadata-Version: 1.1
Name: dcos-shakedown
Version: 1.4.12
Summary: DC/OS testing harness and library
Home-page: https://github.com/dcos/shakedown
Author: Mesosphere QE
Author-email: qe-team@mesosphere.com
License: Apache 2
Platform: UNKNOWN
Classifier: Development Status :: 4 - Beta
Classifier: Intended Audience :: Developers
Classifier: Intended Audience :: Information Technology
Classifier: Topic :: Software Development :: User Interfaces
Classifier: License :: OSI Approved :: Apache Software License
Classifier: Programming Language :: Python :: 3
Classifier: Programming Language :: Python :: 3.5
